Scripts/Spotify.py
Scripts/__init__.py
my_tests/__init__.py
my_tests/test_runDaily.py
my_tests/test_runHourly.py
Spotify_recommendation_FF-0.1.0.dist-info/METADATA
Spotify_recommendation_FF-0.1.0.dist-info/WHEEL
Spotify_recommendation_FF-0.1.0.dist-info/top_level.txt
Spotify_recommendation_FF-0.1.0.dist-info/RECORD
